runescape_text/__init__.py
runescape_text/runescape_text.py
runescape_text/data/runescape_uf.ttf
runescape_text-2.1.0.dist-info/licenses/LICENSE
runescape_text-2.1.0.dist-info/METADATA
runescape_text-2.1.0.dist-info/WHEEL
runescape_text-2.1.0.dist-info/top_level.txt
runescape_text-2.1.0.dist-info/RECORD
