Metadata-Version: 2.4
Name: runescape-text
Version: 2.1.0
Summary: A program for generating runescape-chat-like images of text.
Home-page: https://github.com/sircinnamon/runescape-text
Author: Riley Lahd
Author-email: sircinnamon@gmail.com
Classifier: Programming Language :: Python :: 3
Classifier: License :: OSI Approved :: Apache Software License
Classifier: Operating System :: OS Independent
Requires-Python: >=3.6
License-File: LICENSE
Requires-Dist: pillow>=10
Dynamic: author
Dynamic: author-email
Dynamic: classifier
Dynamic: description
Dynamic: description-content-type
Dynamic: home-page
Dynamic: license-file
Dynamic: requires-dist
Dynamic: requires-python
Dynamic: summary
